setup.py
distributions/Binomialdistribution.py
distributions/Gaussiandistribution.py
distributions/Generaldistribution.py
distributions/__init__.py
stat_distributions_for_testing_only.egg-info/PKG-INFO
stat_distributions_for_testing_only.egg-info/SOURCES.txt
stat_distributions_for_testing_only.egg-info/dependency_links.txt
stat_distributions_for_testing_only.egg-info/not-zip-safe
stat_distributions_for_testing_only.egg-info/top_level.txt